opstools/__init__.py
opstools/cli.py
opstools/aws/__init__.py
opstools/aws/allow_me.py
opstools/aws/commands.py
opstools/aws/ec2_list.py
opstools/aws/lb_logs.py
opstools/aws/sg_report.py
opstools/file/__init__.py
opstools/file/commands.py
opstools/file/hosts.py
opstools/file/log_search.py
opstools/helpers/helper_functions.py
opstools/url/__init__.py
opstools/url/commands.py
opstools/url/stresstest.py
opstools-1.0.1.dist-info/LICENSE.txt
opstools-1.0.1.dist-info/METADATA
opstools-1.0.1.dist-info/WHEEL
opstools-1.0.1.dist-info/entry_points.txt
opstools-1.0.1.dist-info/top_level.txt
opstools-1.0.1.dist-info/RECORD
